RobotMovingPanel/argsParser.py
RobotMovingPanel/config.py
RobotMovingPanel/movingPanel.py
PulseMovingPanel-0.0.1.dist-info/LICENSE
PulseMovingPanel-0.0.1.dist-info/METADATA
PulseMovingPanel-0.0.1.dist-info/WHEEL
PulseMovingPanel-0.0.1.dist-info/entry_points.txt
PulseMovingPanel-0.0.1.dist-info/top_level.txt
PulseMovingPanel-0.0.1.dist-info/RECORD
